scc_cli/__init__.py
scc_cli/auth.py
scc_cli/bootstrap.py
scc_cli/claude_adapter.py
scc_cli/cli.py
scc_cli/cli_common.py
scc_cli/cli_helpers.py
scc_cli/config.py
scc_cli/confirm.py
scc_cli/console.py
scc_cli/contexts.py
scc_cli/deprecation.py
scc_cli/deps.py
scc_cli/git.py
scc_cli/json_command.py
scc_cli/json_output.py
scc_cli/kinds.py
scc_cli/org_templates.py
scc_cli/output_mode.py
scc_cli/panels.py
scc_cli/platform.py
scc_cli/profiles.py
scc_cli/remote.py
scc_cli/sessions.py
scc_cli/setup.py
scc_cli/source_resolver.py
scc_cli/stats.py
scc_cli/subprocess_utils.py
scc_cli/support_bundle.py
scc_cli/teams.py
scc_cli/theme.py
scc_cli/update.py
scc_cli/validate.py
scc_cli/adapters/__init__.py
scc_cli/adapters/claude_agent_runner.py
scc_cli/adapters/config_normalizer.py
scc_cli/adapters/docker_sandbox_runtime.py
scc_cli/adapters/local_config_store.py
scc_cli/adapters/local_dependency_installer.py
scc_cli/adapters/local_doctor_runner.py
scc_cli/adapters/local_filesystem.py
scc_cli/adapters/local_git_client.py
scc_cli/adapters/local_platform_probe.py
scc_cli/adapters/personal_profile_service_local.py
scc_cli/adapters/requests_fetcher.py
scc_cli/adapters/session_store_json.py
scc_cli/adapters/system_clock.py
scc_cli/adapters/zip_archive_writer.py
scc_cli/application/__init__.py
scc_cli/application/compute_effective_config.py
scc_cli/application/dashboard.py
scc_cli/application/interaction_requests.py
scc_cli/application/personal_profile_policy.py
scc_cli/application/profiles.py
scc_cli/application/start_session.py
scc_cli/application/support_bundle.py
scc_cli/application/sync_marketplace.py
scc_cli/application/launch/__init__.py
scc_cli/application/launch/apply_personal_profile.py
scc_cli/application/launch/finalize_launch.py
scc_cli/application/launch/output_models.py
scc_cli/application/launch/prepare_launch_plan.py
scc_cli/application/launch/select_session.py
scc_cli/application/launch/start_wizard.py
scc_cli/application/sessions/__init__.py
scc_cli-1.7.3.dist-info/METADATA
scc_cli-1.7.3.dist-info/WHEEL
scc_cli-1.7.3.dist-info/entry_points.txt
scc_cli-1.7.3.dist-info/licenses/LICENSE
scc_cli-1.7.3.dist-info/RECORD
