Metadata-Version: 2.4
Name: scc-cli
Version: 1.7.3
Summary: Run Claude Code in Docker sandboxes with team configs and git worktree support
Project-URL: Homepage, https://github.com/CCimen/scc
Project-URL: Documentation, https://github.com/CCimen/scc#readme
Project-URL: Repository, https://github.com/CCimen/scc
Project-URL: Issues, https://github.com/CCimen/scc/issues
Author-email: Cagri Cimen <cagricimeenn@gmail.com>
License-Expression: MIT
License-File: LICENSE
Keywords: ai,claude,cli,docker,git,worktree
Classifier: Development Status :: 4 - Beta
Classifier: Environment :: Console
Classifier: Intended Audience :: Developers
Classifier: License :: OSI Approved :: MIT License
Classifier: Operating System :: OS Independent
Classifier: Programming Language :: Python :: 3
Classifier: Programming Language :: Python :: 3.10
Classifier: Programming Language :: Python :: 3.11
Classifier: Programming Language :: Python :: 3.12
Classifier: Topic :: Software Development
Requires-Python: >=3.10
Requires-Dist: jsonschema>=4.25.1
Requires-Dist: pydantic>=2.0.0
Requires-Dist: pyyaml>=6.0.0
Requires-Dist: readchar>=4.0.0
Requires-Dist: requests>=2.32.5
Requires-Dist: rich>=13.0.0
Requires-Dist: typer>=0.9.0
Provides-Extra: dev
Requires-Dist: mypy>=1.0.0; extra == 'dev'
Requires-Dist: pytest-cov>=4.0.0; extra == 'dev'
Requires-Dist: pytest>=7.0.0; extra == 'dev'
Requires-Dist: ruff>=0.1.0; extra == 'dev'
